quakestats/__init__.py
quakestats/__main__.py
quakestats/health.py
quakestats/manage.py
quakestats/sdk.py
quakestats/core/__init__.py
quakestats/core/collector.py
quakestats/core/ql.py
quakestats/core/wh.py
quakestats/core/game/__init__.py
quakestats/core/game/base.py
quakestats/core/game/gamelog.py
quakestats/core/game/qlevents.py
quakestats/core/game/qlmatch.py
quakestats/core/q3parser/__init__.py
quakestats/core/q3parser/api.py
quakestats/core/q3parser/events.py
quakestats/core/q3parser/parser.py
quakestats/core/q3parser/splitter.py
quakestats/core/q3parser/modparse/__init__.py
quakestats/core/q3parser/modparse/baseq3.py
quakestats/core/q3parser/modparse/edawn.py
quakestats/core/q3parser/modparse/osp.py
quakestats/core/q3toql/__init__.py
quakestats/core/q3toql/api.py
quakestats/core/q3toql/entities.py
quakestats/core/q3toql/transform.py
quakestats/core/qlparser/__init__.py
quakestats/core/qlparser/api.py
quakestats/core/qlparser/splitter.py
quakestats/dataprovider/__init__.py
quakestats/dataprovider/analyze.py
quakestats/dataprovider/analyzer/__init__.py
quakestats/dataprovider/analyzer/badges.py
quakestats/dataprovider/analyzer/events.py
quakestats/dataprovider/analyzer/scores.py
quakestats/dataprovider/analyzer/specials.py
quakestats/dataprovider/analyzer/teams.py
quakestats/datasource/__init__.py
quakestats/datasource/entities.py
quakestats/datasource/mongo2.py
quakestats/scripts/q3-log-watch
quakestats/system/__init__.py
quakestats/system/conf.py
quakestats/system/context.py
quakestats/system/log.py
quakestats/system/qa.py
quakestats/web/__init__.py
quakestats/web/api.py
quakestats/web/app.py
quakestats/web/views.py
quakestats/web/static/css/main-printable.css
quakestats/web/static/css/main.css
quakestats/web/static/img/missing.png
quakestats/web/static/img/quake-clean.svg
quakestats/web/static/img/quake-clean.svg.1
quakestats/web/static/img/quake2.svg
quakestats/web/static/img/vs.png
quakestats/web/static/img/vs.svg
quakestats-1.5.1.dist-info/LICENSE
quakestats-1.5.1.dist-info/METADATA
quakestats-1.5.1.dist-info/WHEEL
quakestats-1.5.1.dist-info/entry_points.txt
quakestats-1.5.1.dist-info/top_level.txt
quakestats-1.5.1.dist-info/RECORD
