Metadata-Version: 2.1
Name: quakestats
Version: 1.5.1
Summary: Quake 3 / Quake Live match processing app
Home-page: https://github.com/brabiega/quakestats
Author: Bartoszer
Author-email: bartoszer@bajt.ovh
License: UNKNOWN
Project-URL: Bug Reports, https://github.com/brabiega/quakestats/issues
Project-URL: Source, https://github.com/brabiega/quakestats
Keywords: quake stats statistics match analysis visualize
Platform: UNKNOWN
Classifier: Development Status :: 4 - Beta
Classifier: License :: OSI Approved :: MIT License
Classifier: Programming Language :: Python :: 3
Requires-Python: >=3.6, <4
Requires-Dist: Flask (>=1.0)
Requires-Dist: Flask-PyMongo
Requires-Dist: click (<7,>6.5)
Requires-Dist: pandas
Requires-Dist: passlib
Requires-Dist: pymongo
Requires-Dist: pyzmq
Requires-Dist: requests
